examples/quickstart.py
ataraxis_video_system/__init__.py
ataraxis_video_system/camera.py
ataraxis_video_system/cli.py
ataraxis_video_system/mcp_server.py
ataraxis_video_system/py.typed
ataraxis_video_system/saver.py
ataraxis_video_system/video_system.py
ataraxis_video_system-2.3.0.dist-info/METADATA
ataraxis_video_system-2.3.0.dist-info/WHEEL
ataraxis_video_system-2.3.0.dist-info/entry_points.txt
ataraxis_video_system-2.3.0.dist-info/licenses/LICENSE
ataraxis_video_system-2.3.0.dist-info/RECORD
