Metadata-Version: 2.4
Name: ataraxis-video-system
Version: 2.3.0
Summary: Interfaces with a wide range of cameras to flexibly record visual stream data as video files.
Project-URL: Homepage, https://github.com/Sun-Lab-NBB/ataraxis-video-system
Project-URL: Documentation, https://ataraxis-video-system-api-docs.netlify.app/
Author: Ivan Kondratyev, Jacob Groner, Natalie Yeung
Maintainer-email: Ivan Kondratyev <ik278@cornell.edu>
License:                     GNU GENERAL PUBLIC LICENSE
License-File: LICENSE
Keywords: FFMPEG,GeniCam,OpenCV,ataraxis,camera interface,video recording,video transcoding
Classifier: Development Status :: 5 - Production/Stable
Classifier: Intended Audience :: Developers
Classifier: License :: OSI Approved :: GNU General Public License v3 or later (GPLv3+)
Classifier: Operating System :: MacOS :: MacOS X
Classifier: Operating System :: Microsoft :: Windows
Classifier: Operating System :: POSIX :: Linux
Classifier: Programming Language :: Python :: 3.12
Classifier: Programming Language :: Python :: 3.13
Classifier: Programming Language :: Python :: 3.14
Classifier: Topic :: Multimedia :: Video
Classifier: Typing :: Typed
Requires-Python: <3.15,>=3.12
Requires-Dist: appdirs<2,>=1
Requires-Dist: ataraxis-base-utilities<6,>=5
Requires-Dist: ataraxis-data-structures<6,>=5
Requires-Dist: ataraxis-time<6,>=5
Requires-Dist: click<9,>=8
Requires-Dist: harvesters<2,>=1
Requires-Dist: httpx<1,>=0.27
Requires-Dist: mcp<2,>=1
Requires-Dist: numpy<3,>=2
Requires-Dist: opencv-python<5,>=4
Requires-Dist: tqdm<5,>=4
Provides-Extra: dev
Requires-Dist: ataraxis-automation<8,>=7; extra == 'dev'
Requires-Dist: tox-uv<2,>=1; extra == 'dev'
Requires-Dist: tox<5,>=4; extra == 'dev'
Requires-Dist: types-appdirs<2,>=1; extra == 'dev'
Requires-Dist: types-tqdm<5,>=4; extra == 'dev'
Requires-Dist: uv<1,>=0; extra == 'dev'
